obstore-0.8.1.dist-info/METADATA
obstore-0.8.1.dist-info/WHEEL
obstore.libs/libgcc_s-b5472b99.so.1
obstore/__init__.py
obstore/_attributes.pyi
obstore/_buffered.pyi
obstore/_bytes.pyi
obstore/_copy.pyi
obstore/_delete.pyi
obstore/_get.pyi
obstore/_head.pyi
obstore/_list.pyi
obstore/_obstore.cpython-310-i386-linux-gnu.so
obstore/_obstore.pyi
obstore/_put.pyi
obstore/_rename.pyi
obstore/_scheme.pyi
obstore/_sign.pyi
obstore/_store/__init__.pyi
obstore/_store/_aws.pyi
obstore/_store/_azure.pyi
obstore/_store/_client.pyi
obstore/_store/_gcs.pyi
obstore/_store/_http.pyi
obstore/_store/_retry.pyi
obstore/auth/__init__.py
obstore/auth/_http.py
obstore/auth/azure.py
obstore/auth/boto3.py
obstore/auth/earthdata.py
obstore/auth/google.py
obstore/auth/planetary_computer.py
obstore/exceptions/__init__.pyi
obstore/fsspec.py
obstore/py.typed
obstore/store.py
obstore-0.8.1.dist-info/RECORD
